hbp_service_client/__init__.py
hbp_service_client/client.py
hbp_service_client/version.py
hbp_service_client/request/__init__.py
hbp_service_client/request/request_builder.py
hbp_service_client/storage_service/__init__.py
hbp_service_client/storage_service/api.py
hbp_service_client/storage_service/client.py
hbp_service_client/storage_service/exceptions.py
hbp_service_client/storage_service/service_locator.py
hbp_service_client-1.1.1.dist-info/METADATA
hbp_service_client-1.1.1.dist-info/RECORD
hbp_service_client-1.1.1.dist-info/WHEEL
hbp_service_client-1.1.1.dist-info/top_level.txt
test/__init__.py
test/hbp_service_client/__init__.py
test/hbp_service_client/test_client.py
test/hbp_service_client/request/__init__.py
test/hbp_service_client/request/test_request_builder.py
test/hbp_service_client/storage_service/__init__.py
test/hbp_service_client/storage_service/test_api.py
test/hbp_service_client/storage_service/test_client.py
