Metadata-Version: 2.1
Name: hbp-service-client
Version: 1.1.1
Summary: Python client for the Human Brain Project REST services.
Home-page: https://github.com/HumanBrainProject/hbp-service-client
Author: HBP Infrastructure Developers
Author-email: platform@humanbrainproject.eu
License: Apache License 2.0
Keywords: hbp,human brain project,collaboratory,library,science
Platform: UNKNOWN
Classifier: Development Status :: 4 - Beta
Classifier: Intended Audience :: Developers
Classifier: Intended Audience :: Science/Research
Classifier: License :: OSI Approved :: Apache Software License
Classifier: Operating System :: OS Independent
Classifier: Programming Language :: Python
Classifier: Programming Language :: Python :: 2
Classifier: Programming Language :: Python :: 3
Classifier: Topic :: Scientific/Engineering :: Bio-Informatics
Classifier: Topic :: Software Development :: Libraries :: Python Modules
Requires-Dist: requests (<3.0,>=2.18)
Requires-Dist: validators
